{"lands":{"autotiles":[],"floors":[{"k":[3,0,0,1,0,50,50,90],"v":{"t":[6,9]}},{"k":[3,0,0,0,0,50,50,90],"v":{"t":[6,9]}},{"k":[3,0,0,3,0,50,50,90],"v":{"t":[6,9]}},{"k":[3,0,0,2,0,50,50,90],"v":{"t":[6,9]}},{"k":[3,0,0,5,0,50,50,90],"v":{"t":[6,9]}},{"k":[3,0,0,4,0,50,50,90],"v":{"t":[6,9]}},{"k":[3,0,0,7,0,50,50,90],"v":{"t":[6,9]}},{"k":[3,0,0,6,0,50,50,90],"v":{"t":[6,9]}},{"k":[3,0,0,9,0,50,50,90],"v":{"t":[6,9]}},{"k":[3,0,0,8,0,50,50,90],"v":{"t":[6,9]}},{"k":[3,0,0,11,0,50,50,90],"v":{"t":[6,9]}},{"k":[3,0,0,10,0,50,50,90],"v":{"t":[6,9]}},{"k":[3,0,0,13,0,50,50,90],"v":{"t":[6,9]}},{"k":[3,0,0,12,0,50,50,90],"v":{"t":[6,9]}},{"k":[3,0,0,15,0,50,50,90],"v":{"t":[6,9]}},{"k":[3,0,0,14,0,50,50,90],"v":{"t":[6,9]}},{"k":[0,0,0,0,0],"v":{"t":[2,0]}},{"k":[0,0,0,2,0],"v":{"t":[2,0]}},{"k":[1,0,0,1,0],"v":{"t":[2,0]}},{"k":[2,0,0,0,0],"v":{"t":[2,0]}},{"k":[0,0,0,1,0],"v":{"t":[2,0]}},{"k":[1,0,0,0,0],"v":{"t":[2,0]}},{"k":[0,0,0,4,0],"v":{"t":[2,0]}},{"k":[1,0,0,3,0],"v":{"t":[2,0]}},{"k":[2,0,0,2,0],"v":{"t":[2,0]}},{"k":[4,0,0,0,0],"v":{"t":[2,0]}},{"k":[0,0,0,3,0],"v":{"t":[2,0]}},{"k":[1,0,0,2,0],"v":{"t":[2,0]}},{"k":[2,0,0,1,0],"v":{"t":[2,0]}},{"k":[2,0,0,4,0],"v":{"t":[2,0]}},{"k":[4,0,0,2,0],"v":{"t":[2,0]}},{"k":[1,0,0,5,0],"v":{"t":[2,0]}},{"k":[5,0,0,1,0],"v":{"t":[2,0]}},{"k":[0,0,0,6,0],"v":{"t":[2,0]}},{"k":[6,0,0,0,0],"v":{"t":[2,0]}},{"k":[0,1,0,5,0],"v":{"t":[0,0]}},{"k":[1,0,0,4,0],"v":{"t":[2,0]}},{"k":[2,0,0,3,0],"v":{"t":[2,0]}},{"k":[4,0,0,1,0],"v":{"t":[2,0]}},{"k":[0,0,0,5,0],"v":{"t":[2,0]}},{"k":[5,0,0,0,0],"v":{"t":[2,0]}},{"k":[0,1,0,4,0],"v":{"t":[0,0]}},{"k":[4,0,0,4,0],"v":{"t":[2,0]}},{"k":[5,0,0,3,0],"v":{"t":[2,0]}},{"k":[2,0,0,6,0],"v":{"t":[2,0]}},{"k":[6,0,0,2,0],"v":{"t":[2,0]}},{"k":[1,0,0,7,0],"v":{"t":[2,0]}},{"k":[0,0,0,8,0],"v":{"t":[2,0]}},{"k":[6,1,0,1,0],"v":{"t":[0,0]}},{"k":[5,1,0,2,0],"v":{"t":[0,0]}},{"k":[1,1,0,6,0],"v":{"t":[0,0]}},{"k":[0,1,0,7,0],"v":{"t":[0,0]}},{"k":[4,0,0,3,0],"v":{"t":[2,0]}},{"k":[2,0,0,5,0],"v":{"t":[2,0]}},{"k":[5,0,0,2,0],"v":{"t":[2,0]}},{"k":[1,0,0,6,0],"v":{"t":[2,0]}},{"k":[6,0,0,1,0],"v":{"t":[2,0]}},{"k":[0,0,0,7,0],"v":{"t":[2,0]}},{"k":[6,1,0,0,0],"v":{"t":[0,0]}},{"k":[5,1,0,1,0],"v":{"t":[0,0]}},{"k":[0,1,0,6,0],"v":{"t":[0,0]}},{"k":[1,1,0,5,0],"v":{"t":[0,0]}},{"k":[6,0,0,4,0],"v":{"t":[2,0]}},{"k":[5,0,0,5,0],"v":{"t":[2,0]}},{"k":[4,0,0,6,0],"v":{"t":[2,0]}},{"k":[2,0,0,8,0],"v":{"t":[2,0]}},{"k":[1,0,0,9,0],"v":{"t":[2,0]}},{"k":[0,0,0,10,0],"v":{"t":[2,0]}},{"k":[6,1,0,3,0],"v":{"t":[0,0]}},{"k":[5,1,0,4,0],"v":{"t":[0,0]}},{"k":[4,1,0,5,0],"v":{"t":[0,0]}},{"k":[6,2,0,2,0],"v":{"t":[0,0]}},{"k":[0,1,0,9,0],"v":{"t":[0,0]}},{"k":[1,1,0,8,0],"v":{"t":[0,0]}},{"k":[0,2,0,8,0],"v":{"t":[0,0]}},{"k":[5,0,0,4,0],"v":{"t":[2,0]}},{"k":[4,0,0,5,0],"v":{"t":[2,0]}},{"k":[6,0,0,3,0],"v":{"t":[2,0]}},{"k":[2,0,0,7,0],"v":{"t":[2,0]}},{"k":[1,0,0,8,0],"v":{"t":[2,0]}},{"k":[0,0,0,9,0],"v":{"t":[2,0]}},{"k":[6,1,0,2,0],"v":{"t":[0,0]}},{"k":[5,1,0,3,0],"v":{"t":[0,0]}},{"k":[1,1,0,7,0],"v":{"t":[0,0]}},{"k":[0,1,0,8,0],"v":{"t":[0,0]}},{"k":[0,2,0,7,0],"v":{"t":[0,0]}},{"k":[6,0,0,6,0],"v":{"t":[2,0]}},{"k":[5,0,0,7,0],"v":{"t":[2,0]}},{"k":[4,0,0,8,0],"v":{"t":[2,0]}},{"k":[2,0,0,10,0],"v":{"t":[2,0]}},{"k":[1,0,0,11,0],"v":{"t":[2,0]}},{"k":[0,0,0,12,0],"v":{"t":[2,0]}},{"k":[6,1,0,5,0],"v":{"t":[0,0]}},{"k":[5,1,0,6,0],"v":{"t":[0,0]}},{"k":[6,2,0,4,0],"v":{"t":[0,0]}},{"k":[5,2,0,5,0],"v":{"t":[0,0]}},{"k":[0,1,0,11,0],"v":{"t":[0,0]}},{"k":[2,1,0,9,0],"v":{"t":[0,0]}},{"k":[0,2,0,10,0],"v":{"t":[0,0]}},{"k":[6,0,0,5,0],"v":{"t":[2,0]}},{"k":[5,0,0,6,0],"v":{"t":[2,0]}},{"k":[4,0,0,7,0],"v":{"t":[2,0]}},{"k":[2,0,0,9,0],"v":{"t":[2,0]}},{"k":[1,0,0,10,0],"v":{"t":[2,0]}},{"k":[0,0,0,11,0],"v":{"t":[2,0]}},{"k":[6,1,0,4,0],"v":{"t":[0,0]}},{"k":[4,1,0,6,0],"v":{"t":[0,0]}},{"k":[5,1,0,5,0],"v":{"t":[0,0]}},{"k":[6,2,0,3,0],"v":{"t":[0,0]}},{"k":[5,2,0,4,0],"v":{"t":[0,0]}},{"k":[0,1,0,10,0],"v":{"t":[0,0]}},{"k":[1,1,0,9,0],"v":{"t":[0,0]}},{"k":[0,2,0,9,0],"v":{"t":[0,0]}},{"k":[6,0,0,8,0],"v":{"t":[2,0]}},{"k":[5,0,0,9,0],"v":{"t":[2,0]}},{"k":[4,0,0,10,0],"v":{"t":[2,0]}},{"k":[2,0,0,12,0],"v":{"t":[2,0]}},{"k":[1,0,0,13,0],"v":{"t":[2,0]}},{"k":[0,0,0,14,0],"v":{"t":[2,0]}},{"k":[6,1,0,7,0],"v":{"t":[0,0]}},{"k":[5,1,0,8,0],"v":{"t":[0,0]}},{"k":[6,2,0,6,0],"v":{"t":[0,0]}},{"k":[5,2,0,7,0],"v":{"t":[0,0]}},{"k":[1,1,0,12,0],"v":{"t":[0,0]}},{"k":[0,1,0,13,0],"v":{"t":[0,0]}},{"k":[6,0,0,7,0],"v":{"t":[2,0]}},{"k":[5,0,0,8,0],"v":{"t":[2,0]}},{"k":[4,0,0,9,0],"v":{"t":[2,0]}},{"k":[2,0,0,11,0],"v":{"t":[2,0]}},{"k":[1,0,0,12,0],"v":{"t":[2,0]}},{"k":[0,0,0,13,0],"v":{"t":[2,0]}},{"k":[6,1,0,6,0],"v":{"t":[0,0]}},{"k":[5,1,0,7,0],"v":{"t":[0,0]}},{"k":[6,2,0,5,0],"v":{"t":[0,0]}},{"k":[5,2,0,6,0],"v":{"t":[0,0]}},{"k":[0,1,0,12,0],"v":{"t":[0,0]}},{"k":[0,2,0,11,0],"v":{"t":[0,0]}},{"k":[6,0,0,10,0],"v":{"t":[2,0]}},{"k":[5,0,0,11,0],"v":{"t":[2,0]}},{"k":[4,0,0,12,0],"v":{"t":[2,0]}},{"k":[2,0,0,14,0],"v":{"t":[2,0]}},{"k":[1,0,0,15,0],"v":{"t":[2,0]}},{"k":[6,1,0,9,0],"v":{"t":[0,0]}},{"k":[5,1,0,10,0],"v":{"t":[0,0]}},{"k":[6,2,0,8,0],"v":{"t":[0,0]}},{"k":[5,2,0,9,0],"v":{"t":[0,0]}},{"k":[6,3,0,7,0],"v":{"t":[0,0]}},{"k":[6,0,0,9,0],"v":{"t":[2,0]}},{"k":[5,0,0,10,0],"v":{"t":[2,0]}},{"k":[4,0,0,11,0],"v":{"t":[2,0]}},{"k":[2,0,0,13,0],"v":{"t":[2,0]}},{"k":[1,0,0,14,0],"v":{"t":[2,0]}},{"k":[6,1,0,8,0],"v":{"t":[0,0]}},{"k":[5,1,0,9,0],"v":{"t":[0,0]}},{"k":[6,2,0,7,0],"v":{"t":[0,0]}},{"k":[5,2,0,8,0],"v":{"t":[0,0]}},{"k":[6,3,0,6,0],"v":{"t":[0,0]}},{"k":[0,1,0,14,0],"v":{"t":[0,0]}},{"k":[0,0,0,15,0],"v":{"t":[1,6]}},{"k":[6,0,0,12,0],"v":{"t":[2,0]}},{"k":[5,0,0,13,0],"v":{"t":[2,0]}},{"k":[4,0,0,14,0],"v":{"t":[2,0]}},{"k":[5,1,0,12,0],"v":{"t":[0,0]}},{"k":[6,1,0,11,0],"v":{"t":[0,0]}},{"k":[6,2,0,10,0],"v":{"t":[0,0]}},{"k":[5,2,0,11,0],"v":{"t":[0,0]}},{"k":[6,3,0,9,0],"v":{"t":[0,0]}},{"k":[6,0,0,11,0],"v":{"t":[2,0]}},{"k":[5,0,0,12,0],"v":{"t":[2,0]}},{"k":[4,0,0,13,0],"v":{"t":[2,0]}},{"k":[2,0,0,15,0],"v":{"t":[2,0]}},{"k":[5,1,0,11,0],"v":{"t":[0,0]}},{"k":[6,1,0,10,0],"v":{"t":[0,0]}},{"k":[4,1,0,12,0],"v":{"t":[0,0]}},{"k":[6,2,0,9,0],"v":{"t":[0,0]}},{"k":[5,2,0,10,0],"v":{"t":[0,0]}},{"k":[6,3,0,8,0],"v":{"t":[0,0]}},{"k":[6,0,0,14,0],"v":{"t":[2,0]}},{"k":[5,0,0,15,0],"v":{"t":[2,0]}},{"k":[6,1,0,13,0],"v":{"t":[0,0]}},{"k":[5,1,0,14,0],"v":{"t":[0,0]}},{"k":[6,2,0,12,0],"v":{"t":[0,0]}},{"k":[6,0,0,13,0],"v":{"t":[2,0]}},{"k":[5,0,0,14,0],"v":{"t":[2,0]}},{"k":[4,0,0,15,0],"v":{"t":[2,0]}},{"k":[5,1,0,13,0],"v":{"t":[0,0]}},{"k":[6,1,0,12,0],"v":{"t":[0,0]}},{"k":[6,2,0,11,0],"v":{"t":[0,0]}},{"k":[5,2,0,12,0],"v":{"t":[0,0]}},{"k":[6,1,0,15,0],"v":{"t":[0,0]}},{"k":[6,2,0,14,0],"v":{"t":[0,0]}},{"k":[6,0,0,15,0],"v":{"t":[2,0]}},{"k":[6,1,0,14,0],"v":{"t":[0,0]}},{"k":[6,2,0,13,0],"v":{"t":[0,0]}}]},"moun":{"a":[{"k":[0,0,0,4,0],"v":{"b":true,"sid":5}},{"k":[6,0,0,0,0],"v":{"b":true,"sid":5}},{"k":[5,0,0,1,0],"v":{"b":true,"r":true,"sid":5}},{"k":[0,0,0,6,0],"v":{"b":true,"r":true,"sid":5,"t":true}},{"k":[1,0,0,5,0],"v":{"b":true,"l":true,"sid":5}},{"k":[0,0,0,5,0],"v":{"b":true,"r":true,"sid":5,"t":true}},{"k":[6,0,0,2,0],"v":{"b":true,"l":true,"sid":5,"t":true}},{"k":[5,0,0,3,0],"v":{"b":true,"r":true,"sid":5,"t":true}},{"k":[1,0,0,7,0],"v":{"b":true,"l":true,"sid":5,"t":true}},{"k":[0,0,0,8,0],"v":{"b":true,"r":true,"sid":5,"t":true}},{"k":[0,1,0,7,0],"v":{"b":true,"sid":5}},{"k":[6,0,0,1,0],"v":{"b":true,"l":true,"sid":5,"t":true}},{"k":[5,0,0,2,0],"v":{"b":true,"r":true,"sid":5,"t":true}},{"k":[1,0,0,6,0],"v":{"b":true,"l":true,"sid":5,"t":true}},{"k":[0,0,0,7,0],"v":{"b":true,"r":true,"sid":5,"t":true}},{"k":[6,0,0,4,0],"v":{"b":true,"l":true,"sid":5,"t":true}},{"k":[4,0,0,6,0],"v":{"r":true,"sid":5,"t":true}},{"k":[5,0,0,5,0],"v":{"b":true,"l":true,"r":true,"sid":5,"t":true}},{"k":[6,1,0,3,0],"v":{"b":true,"sid":5,"t":true}},{"k":[5,1,0,4,0],"v":{"b":true,"r":true,"sid":5}},{"k":[0,0,0,10,0],"v":{"b":true,"sid":5,"t":true}},{"k":[1,0,0,9,0],"v":{"l":true,"r":true,"sid":5,"t":true}},{"k":[0,1,0,9,0],"v":{"b":true,"sid":5,"t":true}},{"k":[6,0,0,3,0],"v":{"b":true,"l":true,"sid":5,"t":true}},{"k":[5,0,0,4,0],"v":{"b":true,"r":true,"sid":5,"t":true}},{"k":[4,0,0,5,0],"v":{"b":true,"r":true,"sid":5}},{"k":[6,1,0,2,0],"v":{"b":true,"sid":5}},{"k":[0,0,0,9,0],"v":{"b":true,"r":true,"sid":5,"t":true}},{"k":[1,0,0,8,0],"v":{"b":true,"l":true,"sid":5,"t":true}},{"k":[0,1,0,8,0],"v":{"b":true,"sid":5,"t":true}},{"k":[6,0,0,6,0],"v":{"b":true,"l":true,"sid":5,"t":true}},{"k":[5,0,0,7,0],"v":{"b":true,"r":true,"sid":5,"t":true}},{"k":[6,1,0,5,0],"v":{"b":true,"l":true,"sid":5,"t":true}},{"k":[5,1,0,6,0],"v":{"b":true,"r":true,"sid":5,"t":true}},{"k":[0,0,0,12,0],"v":{"b":true,"r":true,"sid":5,"t":true}},{"k":[0,1,0,11,0],"v":{"sid":5,"t":true}},{"k":[6,0,0,5,0],"v":{"b":true,"l":true,"sid":5,"t":true}},{"k":[5,0,0,6,0],"v":{"b":true,"l":true,"r":true,"sid":5,"t":true}},{"k":[6,1,0,4,0],"v":{"b":true,"l":true,"sid":5,"t":true}},{"k":[5,1,0,5,0],"v":{"b":true,"r":true,"sid":5,"t":true}},{"k":[0,0,0,11,0],"v":{"b":true,"sid":5,"t":true}},{"k":[2,0,0,9,0],"v":{"l":true,"sid":5}},{"k":[0,1,0,10,0],"v":{"b":true,"sid":5,"t":true}},{"k":[6,0,0,8,0],"v":{"b":true,"l":true,"sid":5,"t":true}},{"k":[5,0,0,9,0],"v":{"b":true,"r":true,"sid":5,"t":true}},{"k":[6,1,0,7,0],"v":{"b":true,"l":true,"sid":5,"t":true}},{"k":[5,1,0,8,0],"v":{"b":true,"r":true,"sid":5,"t":true}},{"k":[6,2,0,6,0],"v":{"b":true,"sid":5}},{"k":[0,0,0,14,0],"v":{"sid":5,"t":true}},{"k":[6,0,0,7,0],"v":{"b":true,"l":true,"sid":5,"t":true}},{"k":[5,0,0,8,0],"v":{"b":true,"r":true,"sid":5,"t":true}},{"k":[6,1,0,6,0],"v":{"b":true,"l":true,"sid":5,"t":true}},{"k":[5,1,0,7,0],"v":{"b":true,"r":true,"sid":5,"t":true}},{"k":[1,0,0,12,0],"v":{"l":true,"sid":5}},{"k":[0,0,0,13,0],"v":{"b":true,"sid":5,"t":true}},{"k":[5,0,0,11,0],"v":{"b":true,"r":true,"sid":5,"t":true}},{"k":[6,0,0,10,0],"v":{"b":true,"l":true,"sid":5,"t":true}},{"k":[4,0,0,12,0],"v":{"r":true,"sid":5}},{"k":[6,1,0,9,0],"v":{"b":true,"l":true,"sid":5,"t":true}},{"k":[5,1,0,10,0],"v":{"b":true,"r":true,"sid":5,"t":true}},{"k":[6,2,0,8,0],"v":{"b":true,"sid":5,"t":true}},{"k":[6,0,0,9,0],"v":{"b":true,"l":true,"sid":5,"t":true}},{"k":[5,0,0,10,0],"v":{"b":true,"r":true,"sid":5,"t":true}},{"k":[6,1,0,8,0],"v":{"b":true,"l":true,"sid":5,"t":true}},{"k":[5,1,0,9,0],"v":{"b":true,"r":true,"sid":5,"t":true}},{"k":[6,2,0,7,0],"v":{"b":true,"sid":5,"t":true}},{"k":[5,0,0,13,0],"v":{"b":true,"r":true,"sid":5,"t":true}},{"k":[6,0,0,12,0],"v":{"b":true,"l":true,"sid":5,"t":true}},{"k":[6,1,0,11,0],"v":{"b":true,"l":true,"sid":5,"t":true}},{"k":[5,1,0,12,0],"v":{"r":true,"sid":5,"t":true}},{"k":[5,0,0,12,0],"v":{"b":true,"l":true,"r":true,"sid":5,"t":true}},{"k":[6,0,0,11,0],"v":{"b":true,"l":true,"sid":5,"t":true}},{"k":[6,1,0,10,0],"v":{"b":true,"l":true,"sid":5,"t":true}},{"k":[5,1,0,11,0],"v":{"b":true,"r":true,"sid":5,"t":true}},{"k":[6,2,0,9,0],"v":{"sid":5,"t":true}},{"k":[6,0,0,14,0],"v":{"b":true,"l":true,"sid":5,"t":true}},{"k":[6,1,0,13,0],"v":{"b":true,"sid":5,"t":true}},{"k":[6,0,0,13,0],"v":{"b":true,"l":true,"sid":5,"t":true}},{"k":[5,0,0,14,0],"v":{"r":true,"sid":5,"t":true}},{"k":[6,1,0,12,0],"v":{"b":true,"l":true,"sid":5,"t":true}},{"k":[6,0,0,15,0],"v":{"sid":5,"t":true}},{"k":[6,1,0,14,0],"v":{"sid":5,"t":true}}],"o":[]},"objs":{"list":[{"k":[3,0,0,1,0],"v":{"events":[{"id":2,"name":"Hero touch","p":[],"r":{"1":{"bh":true,"c":[{"command":[8,"",-1,0,0,1,"Телепорт обратно"],"kind":1},{"command":[3,2,3,5,"-",1,"Да","-",1,"Нет"],"kind":31},{"children":[{"command":[8,"",-1,0,0,1,"Ок телепортирую"],"kind":1},{"command":[7,0,0,4,34,1,0,37,0,0,0],"kind":20}],"command":[1],"kind":32},{"children":[{"command":[8,"",-1,0,0,1,"Хорошо"],"kind":1}],"command":[2],"kind":32},{"command":[],"kind":33}]}},"sys":false}],"hId":-1,"id":2,"name":"OBJ0002","ooepf":false,"states":[{"cam":true,"climb":false,"dir":false,"gid":-1,"gk":0,"id":1,"move":true,"name":"state 1","pix":true,"pos":false,"stop":false,"sx":{"k":12,"v":1},"sy":{"k":12,"v":1},"sz":{"k":12,"v":1},"through":false,"x":0,"y":0}]}},{"k":[4,0,0,1,0],"v":{"hId":2,"id":5,"name":"hero","ooepf":false}},{"k":[2,0,0,14,0],"v":{"events":[{"id":2,"name":"Hero touch","p":[],"r":{"1":{"bh":true,"c":[{"command":[8,"",-1,0,0,1,"Ты в пещере"],"kind":1},{"command":[7,-1],"kind":41}]}},"sys":false}],"hId":-1,"id":4,"name":"OBJ0004","ooepf":false,"states":[{"cam":true,"climb":false,"dir":false,"gid":-1,"gk":0,"id":1,"move":true,"name":"state 1","pix":true,"pos":false,"stop":false,"sx":{"k":12,"v":1},"sy":{"k":12,"v":1},"sz":{"k":12,"v":1},"through":false,"x":0,"y":0}]}},{"k":[2,0,0,13,0],"v":{"events":[{"id":2,"name":"Hero touch","p":[],"r":{"1":{"bh":true,"c":[{"command":[8,"",-1,0,0,1,"Привет, я Чирвяк!"],"kind":1},{"command":[3,2,3,5,"-",1,"Кто ты?"],"kind":31},{"children":[{"command":[8,"",-1,0,0,1,"Я проверякер . Я проверяю вагонетки"],"kind":1},{"command":[3,2,3,5,"-",1,"Понятно","-",1,"А почему проверякер?"],"kind":31},{"children":[{"command":[8,"",-1,0,0,1,"Пока"],"kind":1}],"command":[1],"kind":32},{"children":[{"command":[8,"",-1,0,0,1,"Я сам придумал"],"kind":1}],"command":[2],"kind":32},{"command":[],"kind":33}],"command":[1],"kind":32},{"command":[],"kind":33}]}},"sys":false}],"hId":-1,"id":1,"name":"OBJ0001","ooepf":false,"states":[{"cam":true,"climb":false,"dir":false,"gid":43,"gk":4,"id":1,"move":true,"name":"state 1","pix":true,"pos":false,"stop":false,"sx":{"k":12,"v":1},"sy":{"k":12,"v":1},"sz":{"k":12,"v":1},"through":false,"x":0,"y":0}]}},{"k":[0,0,0,15,0],"v":{"events":[{"id":2,"name":"Hero touch","p":[],"r":{"1":{"bh":true,"c":[{"command":[7,0,0,6,1,0,0,1,0,0,0],"kind":20}]}},"sys":false}],"hId":-1,"id":6,"name":"OBJ0006","ooepf":false,"states":[{"cam":true,"climb":false,"dir":false,"gid":-1,"gk":0,"id":1,"move":true,"name":"state 1","pix":true,"pos":false,"stop":false,"sx":{"k":12,"v":1},"sy":{"k":12,"v":1},"sz":{"k":12,"v":1},"through":false,"x":0,"y":0}]}},{"k":[1,0,0,14,0],"v":{"events":[{"id":2,"name":"Hero touch","p":[],"r":{"1":{"bh":true,"c":[{"command":[8,"",-1,0,0,1,"Ты в пещере"],"kind":1},{"command":[7,-1],"kind":41}]}},"sys":false}],"hId":-1,"id":3,"name":"OBJ0004","ooepf":false,"states":[{"cam":true,"climb":false,"dir":false,"gid":-1,"gk":0,"id":1,"move":true,"name":"state 1","pix":true,"pos":false,"stop":false,"sx":{"k":12,"v":1},"sy":{"k":12,"v":1},"sz":{"k":12,"v":1},"through":false,"x":0,"y":0}]}},{"k":[4,0,0,14,0],"v":{"events":[{"id":2,"name":"Hero touch","p":[],"r":{"1":{"bh":true,"c":[{"command":[8,"",-1,0,0,1,"Ты в пещере"],"kind":1},{"command":[7,-1],"kind":41}]}},"sys":false}],"hId":-1,"id":8,"name":"OBJ0004","ooepf":false,"states":[{"cam":true,"climb":false,"dir":false,"gid":-1,"gk":0,"id":1,"move":true,"name":"state 1","pix":true,"pos":false,"stop":false,"sx":{"k":12,"v":1},"sy":{"k":12,"v":1},"sz":{"k":12,"v":1},"through":false,"x":0,"y":0}]}},{"k":[3,0,0,14,0],"v":{"events":[{"id":2,"name":"Hero touch","p":[],"r":{"1":{"bh":true,"c":[{"command":[8,"",-1,0,0,1,"Ты в пещере"],"kind":1},{"command":[7,-1],"kind":41}]}},"sys":false}],"hId":-1,"id":7,"name":"OBJ0004","ooepf":false,"states":[{"cam":true,"climb":false,"dir":false,"gid":-1,"gk":0,"id":1,"move":true,"name":"state 1","pix":true,"pos":false,"stop":false,"sx":{"k":12,"v":1},"sy":{"k":12,"v":1},"sz":{"k":12,"v":1},"through":false,"x":0,"y":0}]}}]},"objs3d":{"a":[{"k":[3,0,0,0,0,50,50,90],"v":{"did":113}},{"k":[3,0,0,9,0,50,50,90],"v":{"did":113}}],"o":[]},"sprites":{"list":[{"k":[3,0,0,15,0],"v":{"f":false,"k":5,"t":[6,12,2,2]}},{"k":[6,1,0,13,0],"v":{"f":false,"k":5,"t":[7,1,1,1]}},{"k":[4,0,0,2,0,50,50,90],"v":{"k":5,"t":[5,1,1,1]}},{"k":[0,1,0,5,0,50,50,90],"v":{"f":false,"k":5,"t":[5,1,1,1]}},{"k":[5,0,0,0,0,50,50,90],"v":{"k":5,"t":[5,1,1,1]}},{"k":[2,0,0,6,0,50,50,90],"v":{"f":false,"k":5,"t":[1,1,1,1]}},{"k":[6,1,0,0,0,50,50,90],"v":{"k":5,"t":[1,1,1,1]}},{"k":[1,1,0,8,0,50,50,90],"v":{"f":false,"k":5,"t":[1,1,1,1]}},{"k":[5,1,0,3,0,50,50,90],"v":{"k":5,"t":[4,1,1,1]}},{"k":[0,2,0,7,0,50,50,90],"v":{"k":5,"t":[4,1,1,1]}},{"k":[6,2,0,4,0,50,50,90],"v":{"k":5,"t":[1,1,1,1]}},{"k":[1,0,0,11,0,50,50,90],"v":{"k":5,"t":[4,1,1,1]}},{"k":[4,1,0,6,0,50,50,90],"v":{"k":5,"t":[1,1,1,1]}},{"k":[1,1,0,9,0,50,50,90],"v":{"k":5,"t":[4,1,1,1]}},{"k":[5,2,0,6,0,50,50,90],"v":{"k":5,"t":[7,1,1,1]}},{"k":[4,0,0,9,0,50,50,90],"v":{"k":5,"t":[1,1,1,1]}},{"k":[0,1,0,12,0,50,50,90],"v":{"f":false,"k":5,"t":[1,1,1,1]}},{"k":[5,2,0,9,0,50,50,90],"v":{"k":5,"t":[1,1,1,1]}},{"k":[5,2,0,8,0,50,50,90],"v":{"k":5,"t":[5,1,1,1]}},{"k":[1,0,0,14,0,50,50,90],"v":{"f":false,"k":5,"t":[5,1,1,1]}},{"k":[4,1,0,12,0,50,50,90],"v":{"f":false,"k":5,"t":[5,1,1,1]}},{"k":[6,2,0,11,0,50,50,90],"v":{"k":5,"t":[7,1,1,1]}},{"k":[5,1,0,13,0,50,50,90],"v":{"f":false,"k":5,"t":[7,1,1,1]}},{"k":[3,0,0,0,0],"v":{"k":5,"t":[6,12,2,2]}},{"k":[6,0,0,0,0],"v":{"k":5,"t":[5,1,1,1]}},{"k":[6,1,0,3,0],"v":{"k":5,"t":[4,1,1,1]}}],"overflow":[],"walls":[{"k":[6,0,0,1,0,100,50,90],"v":{"k":1,"w":17}},{"k":[6,0,0,4,0,100,50,90],"v":{"k":1,"w":17}},{"k":[6,0,0,3,0,100,50,90],"v":{"k":1,"w":17}},{"k":[6,0,0,6,0,100,50,90],"v":{"k":1,"w":17}},{"k":[6,0,0,5,0,100,50,90],"v":{"k":1,"w":17}},{"k":[6,0,0,8,0,100,50,90],"v":{"k":1,"w":17}},{"k":[6,0,0,7,0,100,50,90],"v":{"k":1,"w":17}},{"k":[6,0,0,10,0,100,50,90],"v":{"k":1,"w":17}},{"k":[6,0,0,9,0,100,50,90],"v":{"k":1,"w":17}},{"k":[6,0,0,12,0,100,50,90],"v":{"k":1,"w":17}},{"k":[6,0,0,11,0,100,50,90],"v":{"k":1,"w":17}},{"k":[6,0,0,14,0,100,50,90],"v":{"k":1,"w":17}},{"k":[6,0,0,13,0,100,50,90],"v":{"k":1,"w":17}},{"k":[0,0,0,0,0,0,50,90],"v":{"k":2,"w":17}},{"k":[6,0,0,15,0,100,50,90],"v":{"k":0,"w":17}},{"k":[0,0,0,2,0,0,50,90],"v":{"k":1,"w":17}},{"k":[0,0,0,1,0,0,50,90],"v":{"k":1,"w":17}},{"k":[0,0,0,4,0,0,50,90],"v":{"k":1,"w":17}},{"k":[0,0,0,3,0,0,50,90],"v":{"k":1,"w":17}},{"k":[0,0,0,6,0,0,50,90],"v":{"k":1,"w":17}},{"k":[0,0,0,5,0,0,50,90],"v":{"k":1,"w":17}},{"k":[0,0,0,8,0,0,50,90],"v":{"k":1,"w":17}},{"k":[0,0,0,7,0,0,50,90],"v":{"k":1,"w":17}},{"k":[0,0,0,10,0,0,50,90],"v":{"k":1,"w":17}},{"k":[0,0,0,9,0,0,50,90],"v":{"k":1,"w":17}},{"k":[0,0,0,12,0,0,50,90],"v":{"k":1,"w":17}},{"k":[0,0,0,11,0,0,50,90],"v":{"k":1,"w":17}},{"k":[0,0,0,14,0,0,50,90],"v":{"k":1,"w":17}},{"k":[0,0,0,13,0,0,50,90],"v":{"k":1,"w":17}},{"k":[0,0,0,15,0,0,50,90],"v":{"k":0,"w":17}},{"k":[1,0,0,15,0,50,100,0],"v":{"k":1,"w":17}},{"k":[0,0,0,15,0,50,100,0],"v":{"k":0,"w":17}},{"k":[3,0,0,15,0,50,100,0],"v":{"k":1,"w":17}},{"k":[2,0,0,15,0,50,100,0],"v":{"k":1,"w":17}},{"k":[5,0,0,15,0,50,100,0],"v":{"k":1,"w":17}},{"k":[4,0,0,15,0,50,100,0],"v":{"k":1,"w":17}},{"k":[0,0,0,0,0,50,0,0],"v":{"k":0,"w":17}},{"k":[6,0,0,15,0,50,100,0],"v":{"k":2,"w":17}},{"k":[2,0,0,0,0,50,0,0],"v":{"k":1,"w":17}},{"k":[1,0,0,0,0,50,0,0],"v":{"k":1,"w":17}},{"k":[4,0,0,0,0,50,0,0],"v":{"k":1,"w":17}},{"k":[3,0,0,0,0,50,0,0],"v":{"k":1,"w":17}},{"k":[6,0,0,0,0,50,0,0],"v":{"k":2,"w":17}},{"k":[5,0,0,0,0,50,0,0],"v":{"k":1,"w":17}},{"k":[6,0,0,0,0,100,50,90],"v":{"k":2,"w":17}},{"k":[6,0,0,2,0,100,50,90],"v":{"k":1,"w":17}}]}}